shuogg/__init__.py
shuogg/byte_util.py
shuogg/code_util.py
shuogg/date_util.py
shuogg/des_util.py
shuogg/file_util.py
shuogg/ftp_util.py
shuogg/mac_util.py
shuogg/mysql_util.py
shuogg/net.py
shuogg/random_util.py
shuogg/ssh_util.py
shuogg-0.1.dist-info/METADATA
shuogg-0.1.dist-info/WHEEL
shuogg-0.1.dist-info/top_level.txt
shuogg-0.1.dist-info/RECORD
