Metadata-Version: 2.1
Name: shuogg
Version: 0.1
Summary: shuoGG's common utils
Home-page: https://github.com/shuoGG1239/ShuoPyUtils
Author: shuoGG
Author-email: 328893769@qq.com
License: UNKNOWN
Keywords: python util
Platform: UNKNOWN
